ram.v
module ram (
    input        clk,
    input        write_enable,  // 1 = Save to RAM, 0 = Read from RAM
    input  [7:0] address,       // Which of the 256 slots to access
    input  [7:0] write_data,    // The data to save
    output [7:0] read_data      // The data coming out
);

    // Create 256 individual 8-bit memory slots
    reg [7:0] memory [255:0];

    // READ: Happens instantly based on the address wire
    assign read_data = memory[address];

    // WRITE: Happens exactly on the clock tick
    always @(posedge clk) begin
        if (write_enable) begin
            memory[address] <= write_data;
        end
    end

endmodule

alu.v
module alu (
    input  [7:0] a,
    input  [7:0] b,
    input  [1:0] op,
    output reg [7:0] out,
    output       zero      // NEW: The Zero Flag
);

    always @(*) begin
        case (op)
            2'b00: out = a + b;
            2'b01: out = a - b;
            2'b10: out = a & b;
            2'b11: out = a | b;
            default: out = 8'b0;
        endcase
    end

    // The zero flag is physically wired to check if all 8 bits of 'out' are 0
    assign zero = (out == 8'b0);

endmodule

register_file.v
module register_file (
    input        clk,           // The system heartbeat
    input        write_enable,  // 1 = Save data, 0 = Read only
    input  [1:0] write_addr,    // Which register to write to (0 to 3)
    input  [7:0] write_data,    // The actual 8-bit number to save
    input  [1:0] read_addr_a,   // Which register to send to Port A
    input  [1:0] read_addr_b,   // Which register to send to Port B
    output [7:0] read_data_a,   // Data out A (goes to ALU)
    output [7:0] read_data_b    // Data out B (goes to ALU)
);

    // This is the actual physical memory: An array of four 8-bit registers
    reg [7:0] registers [3:0];

    // READ LOGIC: Combinational (happens instantly, no clock needed)
    // Whatever address is requested, instantly output what is in that register.
    assign read_data_a = registers[read_addr_a];
    assign read_data_b = registers[read_addr_b];

    // WRITE LOGIC: Sequential (happens exactly on the clock tick)
    always @(posedge clk) begin
        if (write_enable) begin
            registers[write_addr] <= write_data;
        end
    end

endmodule

decoder.v
module decoder (
    input  [15:0] instruction,

    // Sliced Outputs
    output [3:0]  opcode,
    output [1:0]  rd,      // Destination Register (Only need 2 bits for 0-3)
    output [1:0]  rs1,     // Source Register 1
    output [1:0]  rs2,     // Source Register 2
    output [7:0]  imm      // Immediate Value
);

    // Hard-wire the slices directly to the outputs
    assign opcode = instruction[15:12];
    assign rd     = instruction[9:8];   // We only take the bottom 2 bits of this hex digit
    assign rs1    = instruction[5:4];   // We only take the bottom 2 bits of this hex digit
    assign rs2    = instruction[1:0];   // We only take the bottom 2 bits of this hex digit
    assign imm    = instruction[7:0];   // The bottom 8 bits form a number

endmodule

rom.v
module rom (
    input      [7:0] address,
    output reg [15:0] instruction
);
    always @(*) begin
        case (address)
            8'd0: instruction = 16'hA105; // LOAD R1, 5
            8'd1: instruction = 16'hA205; // LOAD R2, 5
            8'd2: instruction = 16'h9012; // SUB R0, R1, R2
            8'd3: instruction = 16'hF006; // BEQ 6
            8'd4: instruction = 16'hA30A; // LOAD R3, 10
            8'd5: instruction = 16'hFFFF; // HALT
            8'd6: instruction = 16'hA3FF; // LOAD R3, 255
            8'd7: instruction = 16'hFFFF; // HALT
            default: instruction = 16'h0000;
        endcase
    end
endmodule

pc.v
module pc (
    input            clk,
    input            reset,
    input            jump_enable,   // Unconditional Jump (Opcode E)
    input            branch_enable, // Conditional Branch (Opcode F)
    input            zero_flag,     // From the ALU
    input      [7:0] target_addr,   // Where to teleport to
    output reg [7:0] pc_out
);

    always @(posedge clk) begin
        if (reset) begin
            pc_out <= 8'b0;
        // Jump if Opcode E, OR if Opcode F AND the ALU output is zero
        end else if (jump_enable || (branch_enable && zero_flag)) begin
            pc_out <= target_addr;
        end else begin
            pc_out <= pc_out + 1;
        end
    end

endmodule

cpu.v
module cpu (
    input clk,
    input reset
);

    wire [7:0]  pc_addr;
    wire [15:0] instruction;
    wire [3:0]  opcode;
    wire [1:0]  rd, rs1, rs2;
    wire [7:0]  imm;
    
    wire [7:0]  reg_out_a, reg_out_b;
    wire        reg_write_enable;
    wire [7:0]  reg_write_data;
    wire [7:0]  alu_result;
    
    wire [7:0]  ram_read_data;
    wire        ram_write_enable;

    // --- NEW: LOGIC WIRES ---
    wire        jump_enable   = (opcode == 4'hE); 
    wire        branch_enable = (opcode == 4'hF); // Opcode F is BEQ
    wire        zero_flag;                        // Wire coming from ALU
    wire [1:0]  alu_ctrl      = (opcode == 4'h9) ? 2'b01 : 2'b00; // 9 = SUB, everything else defaults to ADD

    // --- CONTROL LOGIC ---
    // Save to register on A(Load), 8(Add), 9(Subtract), or D(Ram Load)
    assign reg_write_enable = (opcode == 4'hA) || (opcode == 4'h8) || (opcode == 4'h9) || (opcode == 4'hD);
    assign ram_write_enable = (opcode == 4'hC);
    
    assign reg_write_data = (opcode == 4'hA) ? imm :
                            (opcode == 4'hD) ? ram_read_data :
                                               alu_result;

    // --- HARDWARE PLACEMENT ---
    
    pc the_pc (
        .clk(clk), .reset(reset), 
        .jump_enable(jump_enable), .branch_enable(branch_enable), 
        .zero_flag(zero_flag), .target_addr(imm), 
        .pc_out(pc_addr)
    );
    
    rom the_rom (.address(pc_addr), .instruction(instruction));
    decoder the_decoder (.instruction(instruction), .opcode(opcode), .rd(rd), .rs1(rs1), .rs2(rs2), .imm(imm));
    
    register_file the_regs (
        .clk(clk), .write_enable(reg_write_enable), .write_addr(rd), 
        .write_data(reg_write_data), .read_addr_a(rs1), .read_addr_b(rs2), 
        .read_data_a(reg_out_a), .read_data_b(reg_out_b)
    );
    
    alu the_alu (
        .a(reg_out_a), .b(reg_out_b), 
        .op(alu_ctrl), // Dynamic ALU control!
        .out(alu_result), 
        .zero(zero_flag) // Hook up the new zero wire
    );
    
    ram the_ram (.clk(clk), .write_enable(ram_write_enable), .address(imm), .write_data(reg_out_a), .read_data(ram_read_data));

endmodule

cpu_trace.vcd
$version Generated by VerilatedVcd $end
$timescale 1ps $end
 $scope module TOP $end
  $var wire 1 9 clk $end
  $var wire 1 : reset $end
  $scope module cpu $end
   $var wire 1 9 clk $end
   $var wire 1 : reset $end
   $var wire 8 # pc_addr [7:0] $end
   $var wire 16 $ instruction [15:0] $end
   $var wire 4 % opcode [3:0] $end
   $var wire 2 & rd [1:0] $end
   $var wire 2 ' rs1 [1:0] $end
   $var wire 2 ( rs2 [1:0] $end
   $var wire 8 ) imm [7:0] $end
   $var wire 8 * reg_out_a [7:0] $end
   $var wire 8 + reg_out_b [7:0] $end
   $var wire 1 , reg_write_enable $end
   $var wire 8 - reg_write_data [7:0] $end
   $var wire 8 . alu_result [7:0] $end
   $var wire 8 / ram_read_data [7:0] $end
   $var wire 1 0 ram_write_enable $end
   $var wire 1 1 jump_enable $end
   $var wire 1 2 branch_enable $end
   $var wire 1 3 zero_flag $end
   $var wire 2 4 alu_ctrl [1:0] $end
   $scope module the_alu $end
    $var wire 8 * a [7:0] $end
    $var wire 8 + b [7:0] $end
    $var wire 2 4 op [1:0] $end
    $var wire 8 . out [7:0] $end
    $var wire 1 3 zero $end
   $upscope $end
   $scope module the_decoder $end
    $var wire 16 $ instruction [15:0] $end
    $var wire 4 % opcode [3:0] $end
    $var wire 2 & rd [1:0] $end
    $var wire 2 ' rs1 [1:0] $end
    $var wire 2 ( rs2 [1:0] $end
    $var wire 8 ) imm [7:0] $end
   $upscope $end
   $scope module the_pc $end
    $var wire 1 9 clk $end
    $var wire 1 : reset $end
    $var wire 1 1 jump_enable $end
    $var wire 1 2 branch_enable $end
    $var wire 1 3 zero_flag $end
    $var wire 8 ) target_addr [7:0] $end
    $var wire 8 # pc_out [7:0] $end
   $upscope $end
   $scope module the_ram $end
    $var wire 1 9 clk $end
    $var wire 1 0 write_enable $end
    $var wire 8 ) address [7:0] $end
    $var wire 8 * write_data [7:0] $end
    $var wire 8 / read_data [7:0] $end
   $upscope $end
   $scope module the_regs $end
    $var wire 1 9 clk $end
    $var wire 1 , write_enable $end
    $var wire 2 & write_addr [1:0] $end
    $var wire 8 - write_data [7:0] $end
    $var wire 2 ' read_addr_a [1:0] $end
    $var wire 2 ( read_addr_b [1:0] $end
    $var wire 8 * read_data_a [7:0] $end
    $var wire 8 + read_data_b [7:0] $end
    $var wire 8 5 registers[0] [7:0] $end
    $var wire 8 6 registers[1] [7:0] $end
    $var wire 8 7 registers[2] [7:0] $end
    $var wire 8 8 registers[3] [7:0] $end
   $upscope $end
   $scope module the_rom $end
    $var wire 8 # address [7:0] $end
    $var wire 16 $ instruction [15:0] $end
   $upscope $end
  $upscope $end
 $upscope $end
$enddefinitions $end


#0
b00000000 #
b1010000100000101 $
b1010 %
b01 &
b00 '
b01 (
b00000101 )
b00000000 *
b00000000 +
1,
b00000101 -
b00000000 .
b00000000 /
00
01
02
13
b00 4
b00000000 5
b00000000 6
b00000000 7
b00000000 8
09
1:
#1
b00000101 +
b00000101 .
03
b00000101 6
19
#2
09
0:
#3
b00000001 #
b1010001000000101 $
b10 &
19
#4
09
#5
b00000010 #
b1001000000010010 $
b1001 %
b00 &
b01 '
b10 (
b00010010 )
b00000101 *
b00000000 -
b00000000 .
13
b01 4
b00000101 7
19
#6
09
#7
b00000011 #
b1111000000000110 $
b1111 %
b00 '
b00000110 )
b00000000 *
0,
b00000101 -
b00000101 .
12
03
b00 4
19
#8
09
#9
b00000100 #
b1010001100001010 $
b1010 %
b11 &
b00001010 )
1,
b00001010 -
02
19
#10
09
#11
b00000101 #
b1111111111111111 $
b1111 %
b11 '
b11 (
b11111111 )
b00001010 *
b00001010 +
0,
b00010100 -
b00010100 .
12
b00001010 8
19
#12
09
#13
b00000110 #
b1010001111111111 $
b1010 %
1,
b11111111 -
02
19
#14
09
#15
b00000111 #
b1111111111111111 $
b1111 %
b11111111 *
b11111111 +
0,
b11111110 -
b11111110 .
12
b11111111 8
19
#16
09
#17
b00001000 #
b0000000000000000 $
b0000 %
b00 &
b00 '
b00 (
b00000000 )
b00000000 *
b00000000 +
b00000000 -
b00000000 .
02
13
19
#18
09
#19
b00001001 #
19
#20
09
#21
b00001010 #
19
