pc.v
module pc (
    input            clk,    // The heartbeat
    input            reset,  // 1 = back to 0, 0 = run normally
    output reg [7:0] pc_out  // The current instruction address
);

    // Trigger on the rising edge of the clock
    always @(posedge clk) begin
        if (reset) begin
            pc_out <= 8'b0;      // Reboot to address 0
        end else begin
            pc_out <= pc_out + 1; // Step to the next instruction
        end
    end

endmodule

pc_trace.vcd
$version Generated by VerilatedVcd $end
$timescale 1ps $end
 $scope module TOP $end
  $var wire 1 # clk $end
  $var wire 1 $ reset $end
  $var wire 8 % pc_out [7:0] $end
  $scope module pc $end
   $var wire 1 # clk $end
   $var wire 1 $ reset $end
   $var wire 8 % pc_out [7:0] $end
  $upscope $end
 $upscope $end
$enddefinitions $end


#0
0#
1$
b00000000 %
#1
1#
#2
0#
0$
#3
1#
b00000001 %
#4
0#
#5
1#
b00000010 %
#6
0#
#7
1#
b00000011 %
#8
0#
#9
1#
b00000100 %
#10
0#
1$
#11
1#
b00000000 %
